newspaper_segmentation_client/__init__.py
newspaper_segmentation_client/clip.py
arcanum_newspaper_segmentation_client-1.8.5.dist-info/LICENSE
arcanum_newspaper_segmentation_client-1.8.5.dist-info/METADATA
arcanum_newspaper_segmentation_client-1.8.5.dist-info/WHEEL
arcanum_newspaper_segmentation_client-1.8.5.dist-info/top_level.txt
arcanum_newspaper_segmentation_client-1.8.5.dist-info/RECORD
