Metadata-Version: 2.1
Name: arcanum-newspaper-segmentation-client
Version: 1.8.5
Summary: Client for Arcanum's Newspaper Segmentation API
Home-page: https://www.arcanum.com/en/newspaper-segmentation/
Author: Biszak Előd (Arcanum Ltd)
Author-email: elod.biszak@arcanum.com
Classifier: Programming Language :: Python :: 3
Classifier: License :: OSI Approved :: MIT License
Classifier: Operating System :: OS Independent
Requires-Python: >=3.8
License-File: LICENSE
Requires-Dist: pillow
Requires-Dist: requests
